PiML-0.6.0.post2.dist-info/RECORD
PiML-0.6.0.post2.dist-info/top_level.txt
PiML-0.6.0.post2.dist-info/LICENSE.md
PiML-0.6.0.post2.dist-info/WHEEL
PiML-0.6.0.post2.dist-info/METADATA
piml/utils.cpython-39-x86_64-linux-gnu.so
piml/plots.cpython-39-x86_64-linux-gnu.so
piml/api.cpython-39-x86_64-linux-gnu.so
piml/exceptions.cpython-39-x86_64-linux-gnu.so
piml/__init__.py
piml/scored_test.cpython-39-x86_64-linux-gnu.so
piml/config/model_configs.cpython-39-x86_64-linux-gnu.so
piml/config/__init__.py
piml/config/highcode_configs.cpython-39-x86_64-linux-gnu.so
piml/config/other_configs.cpython-39-x86_64-linux-gnu.so
piml/diagnoser/weakspot.cpython-39-x86_64-linux-gnu.so
piml/diagnoser/utils.cpython-39-x86_64-linux-gnu.so
piml/diagnoser/robustness.cpython-39-x86_64-linux-gnu.so
piml/diagnoser/resilience.cpython-39-x86_64-linux-gnu.so
piml/diagnoser/fairness.cpython-39-x86_64-linux-gnu.so
piml/diagnoser/accuracy.cpython-39-x86_64-linux-gnu.so
piml/diagnoser/overfit.cpython-39-x86_64-linux-gnu.so
piml/diagnoser/__init__.py
piml/diagnoser/base.cpython-39-x86_64-linux-gnu.so
piml/diagnoser/reliability.cpython-39-x86_64-linux-gnu.so
piml/diagnoser/external/fairness_solas.cpython-39-x86_64-linux-gnu.so
piml/diagnoser/external/__init__.py
piml/workflow/eda_api.cpython-39-x86_64-linux-gnu.so
piml/workflow/model_train_api.cpython-39-x86_64-linux-gnu.so
piml/workflow/compare_api.cpython-39-x86_64-linux-gnu.so
piml/workflow/segmented_diagnose_api.cpython-39-x86_64-linux-gnu.so
piml/workflow/data_api.cpython-39-x86_64-linux-gnu.so
piml/workflow/data_quality_api.cpython-39-x86_64-linux-gnu.so
piml/workflow/interpret_api.cpython-39-x86_64-linux-gnu.so
piml/workflow/explain_api.cpython-39-x86_64-linux-gnu.so
piml/workflow/diagnose_api.cpython-39-x86_64-linux-gnu.so
piml/workflow/__init__.py
piml/workflow/pipeline.cpython-39-x86_64-linux-gnu.so
piml/workflow/fairness_api/fairness_solas_api.cpython-39-x86_64-linux-gnu.so
piml/workflow/fairness_api/fairness_compare_api.cpython-39-x86_64-linux-gnu.so
piml/workflow/fairness_api/fairness_api.cpython-39-x86_64-linux-gnu.so
piml/workflow/fairness_api/__init__.py
