Metadata-Version: 2.1
Name: PiML
Version: 0.6.0.post2
Summary: A low-code interpretable machine learning toolbox in Python.
Home-page: https://github.com/SelfExplainML/PiML-Toolbox
Author: Sudjianto, Agus and Zhang, Aijun and Yang, Zebin and Su, Yu and Zeng, Ningzhou
License: Apache
Classifier: Programming Language :: Python :: 3.7
Classifier: Programming Language :: Python :: 3.8
Classifier: Programming Language :: Python :: 3.9
Classifier: Programming Language :: Python :: 3.10
Classifier: License :: OSI Approved :: Apache Software License
License-File: LICENSE.md
Requires-Dist: ipykernel
Requires-Dist: ipywidgets (>=7.7.0)
Requires-Dist: joblib (>=1.1.0)
Requires-Dist: ipython (>=7.12.0)
Requires-Dist: numpy (<1.24.0,>=1.21.4)
Requires-Dist: scipy (<=1.10.1,>=1.5.3)
Requires-Dist: pandas (<2.0.0,>=1.3.5)
Requires-Dist: matplotlib (<3.8.0,>=3.1.2)
Requires-Dist: seaborn (>=0.11.2)
Requires-Dist: xlrd (>=1.2.0)
Requires-Dist: scikit-learn (<1.4.0,>=0.24.2)
Requires-Dist: xgboost (>=1.4.2)
Requires-Dist: statsmodels (>=0.12.2)
Requires-Dist: lime (>=0.2.0.1)
Requires-Dist: shap (>=0.39.0)
Requires-Dist: torch (>=1.11.0)
Requires-Dist: pygam (==0.8.0)
Requires-Dist: natsort (>=8.2.0)
Requires-Dist: psutil (>=5.9.0)
Requires-Dist: dill (>=0.3.6)
Requires-Dist: packaging (>=20.5)
Requires-Dist: networkx (>=2.6.3)
Requires-Dist: numba (<0.57.0)
Requires-Dist: jupyter-client (<=7.4.9)
Requires-Dist: optbinning (>=0.17.3)
Requires-Dist: momentchi2
